humbledb/__init__.py
humbledb/_version.py
humbledb/array.py
humbledb/cursor.py
humbledb/document.py
humbledb/errors.py
humbledb/helpers.py
humbledb/index.py
humbledb/maps.py
humbledb/mongo.py
humbledb/report.py
humbledb-6.0.0.dist-info/METADATA
humbledb-6.0.0.dist-info/RECORD
humbledb-6.0.0.dist-info/WHEEL
humbledb-6.0.0.dist-info/top_level.txt
test/test_humbledb/__init__.py
test/test_humbledb/test_array.py
test/test_humbledb/test_cursor.py
test/test_humbledb/test_document.py
test/test_humbledb/test_helpers.py
test/test_humbledb/test_index.py
test/test_humbledb/test_maps.py
test/test_humbledb/test_mongo.py
test/test_humbledb/test_report.py
