Metadata-Version: 2.1
Name: humbledb
Version: 6.0.0
Summary: HumbleDB - MongoDB Object-Document Mapper
Home-page: UNKNOWN
Author: Jacob Alheid
Author-email: jake@about.me
License: UNKNOWN
Platform: UNKNOWN
Classifier: Development Status :: 5 - Production/Stable
Classifier: Intended Audience :: Developers
Classifier: License :: OSI Approved :: Apache Software License
Classifier: Operating System :: OS Independent
Classifier: Programming Language :: Python :: 2.7
Classifier: Programming Language :: Python :: 3.3
Classifier: Programming Language :: Python :: 3.4
Classifier: Programming Language :: Python :: 3.5
Classifier: Programming Language :: Python :: 3.6
Classifier: Topic :: Software Development :: Libraries
Classifier: Topic :: Utilities
Classifier: Topic :: Database
Requires-Dist: pymongo (>=2.0.1)
Requires-Dist: pyconfig
Requires-Dist: pytool (>=3.4.1)
Requires-Dist: six
